vestaboard/__init__.py
vestaboard/characters.py
vestaboard/formatter.py
vestaboard/vbUrls.py
vestaboard-2.0.0.dist-info/licenses/LICENSE
vestaboard-2.0.0.dist-info/METADATA
vestaboard-2.0.0.dist-info/WHEEL
vestaboard-2.0.0.dist-info/top_level.txt
vestaboard-2.0.0.dist-info/RECORD
